Metadata-Version: 2.1
Name: mrnaScan
Version: 0.1.2
Summary: Identify exons and 3'UTR of each reads for full-length mRNA-seq
Home-page: https://github.com/0CBH0/mrnaScan
Author: 0CBH0
Author-email: maodatou88@163.com
License: MIT
Platform: UNKNOWN
Classifier: License :: OSI Approved :: MIT License
Classifier: Programming Language :: Python
Classifier: Programming Language :: Python :: 2
Classifier: Programming Language :: Python :: 3
Requires-Python: >=3.6
License-File: LICENSE
